oneai/__init__.py
oneai/api.py
oneai/classes.py
oneai/clustering.py
oneai/exceptions.py
oneai/parsing.py
oneai/pipeline.py
oneai/scraping.py
oneai/segments.py
oneai/skills.py
oneai_stage-0.0.1.dist-info/LICENSE
oneai_stage-0.0.1.dist-info/METADATA
oneai_stage-0.0.1.dist-info/WHEEL
oneai_stage-0.0.1.dist-info/top_level.txt
oneai_stage-0.0.1.dist-info/RECORD
