Metadata-Version: 2.1
Name: oneai-stage
Version: 0.0.1
Summary: NLP as a Service
Home-page: https://github.com/power-of-language/oneai-sdk-python
Author-email: devrel@oneai.com
Project-URL: Bug Tracker, https://github.com/power-of-language/oneai-sdk-python/issues
Classifier: Programming Language :: Python :: 3
Requires-Python: >=3.6
License-File: LICENSE
Requires-Dist: aiohttp
Requires-Dist: trafilatura
Requires-Dist: validators
Requires-Dist: typing-extensions
Requires-Dist: dataclasses
